voice_gender_recognition/__init__.py
voice_gender_recognition/core.py
voice_gender_recognition/utils.py
voice_gender_recognition-0.1.1.dist-info/LICENSE
voice_gender_recognition-0.1.1.dist-info/METADATA
voice_gender_recognition-0.1.1.dist-info/WHEEL
voice_gender_recognition-0.1.1.dist-info/top_level.txt
voice_gender_recognition-0.1.1.dist-info/RECORD
